PySQLModel/__init__.py
PySQLModel/base.py
PySQLModel/mysql.py
PySQLModel/sqlite.py
PySQLModel-1.2.0.dist-info/LICENSE
PySQLModel-1.2.0.dist-info/METADATA
PySQLModel-1.2.0.dist-info/WHEEL
PySQLModel-1.2.0.dist-info/top_level.txt
PySQLModel-1.2.0.dist-info/RECORD
