Metadata-Version: 2.2
Name: PySQLModel
Version: 1.2.0
Summary: 简单方便的数据库查询包
Author-email: NeverStopDreamingWang <mr_jia_han@qq.com>
License: BSD 3-Clause
Project-URL: github, https://github.com/NeverStopDreamingWang/pysqlmodel
Project-URL: gitee, https://gitee.com/NeverStopDreamingWang/pysqlmodel
Keywords: SQLite,MySQL
Requires-Python: >=3
License-File: LICENSE
Requires-Dist: pymysql>=1.1.1
